pydevelop_docs/__init__.py
pydevelop_docs/autofix.py
pydevelop_docs/build_error_classifier.py
pydevelop_docs/build_monitor.py
pydevelop_docs/builders.py
pydevelop_docs/cli.py
pydevelop_docs/cli_config_consolidation.py
pydevelop_docs/cli_refactor.py
pydevelop_docs/commands.py
pydevelop_docs/config.py
pydevelop_docs/config_debug.py
pydevelop_docs/config_discovery.py
pydevelop_docs/display.py
pydevelop_docs/general_setup.py
pydevelop_docs/hooks.py
pydevelop_docs/interactive.py
pydevelop_docs/link_builder.py
pydevelop_docs/mock_operations.py
pydevelop_docs/package_auditor.py
pydevelop_docs/package_handlers.py
pydevelop_docs/smart_builder.py
pydevelop_docs/sphinx_debug.py
pydevelop_docs/template_manager.py
pydevelop_docs/templates/Makefile
pydevelop_docs/templates/_autoapi_templates/index.rst
pydevelop_docs/templates/_autoapi_templates/python/attribute.rst
pydevelop_docs/templates/_autoapi_templates/python/class.rst
pydevelop_docs/templates/_autoapi_templates/python/data.rst
pydevelop_docs/templates/_autoapi_templates/python/exception.rst
pydevelop_docs/templates/_autoapi_templates/python/function.rst
pydevelop_docs/templates/_autoapi_templates/python/method.rst
pydevelop_docs/templates/_autoapi_templates/python/module.rst
pydevelop_docs/templates/_autoapi_templates/python/package.rst
pydevelop_docs/templates/_autoapi_templates/python/property.rst
pydevelop_docs/templates/_autoapi_templates_BROKEN_BACKUP/python/_base/foundation.j2
pydevelop_docs/templates/_autoapi_templates_BROKEN_BACKUP/python/_base/progressive.j2
pydevelop_docs/templates/_autoapi_templates_BROKEN_BACKUP/python/_components/code_blocks.j2
pydevelop_docs/templates/_autoapi_templates_BROKEN_BACKUP/python/_components/diagrams.j2
pydevelop_docs/templates/_autoapi_templates_BROKEN_BACKUP/python/_components/navigation.j2
pydevelop_docs/templates/_autoapi_templates_BROKEN_BACKUP/python/_components/tooltips.j2
pydevelop_docs/templates/_autoapi_templates_BROKEN_BACKUP/python/_filters/__init__.py
pydevelop_docs-0.1.0.dist-info/METADATA
pydevelop_docs-0.1.0.dist-info/WHEEL
pydevelop_docs-0.1.0.dist-info/entry_points.txt
pydevelop_docs-0.1.0.dist-info/RECORD
