Metadata-Version: 2.3
Name: pydevelop-docs
Version: 0.1.0
Summary: Universal Python documentation generator with 40+ Sphinx extensions pre-configured. Zero-configuration setup for beautiful, professional documentation.
Keywords: documentation,sphinx,python,docs,api,autodoc
Author: William R. Astley
Requires-Python: >=3.12,<3.13
Classifier: Development Status :: 4 - Beta
Classifier: Intended Audience :: Developers
Classifier: License :: OSI Approved :: MIT License
Classifier: Programming Language :: Python :: 3
Classifier: Programming Language :: Python :: 3.12
Classifier: Topic :: Documentation
Classifier: Topic :: Software Development :: Documentation
Requires-Dist: click (>=8.1.7,<9.0.0)
Requires-Dist: furo (>=2024.8.6,<2025.0.0)
Requires-Dist: myst-parser (>=4.0.1,<5.0.0)
Requires-Dist: pyyaml (>=6.0.1,<7.0.0)
Requires-Dist: questionary (>=2.1.0,<3.0.0)
Requires-Dist: rich (>=14.1.0,<15.0.0)
Requires-Dist: seed-intersphinx-mapping (>=1.2.2,<2.0.0)
Requires-Dist: sphinx (==8.2.3)
Requires-Dist: sphinx-collections (>=0.2.0,<0.3.0)
Requires-Dist: sphinx-toolbox (>=3.8.1,<4.0.0)
Requires-Dist: tomlkit (>=0.13.2,<0.14.0)
Project-URL: Documentation, https://pydevelop-docs.readthedocs.io
Project-URL: Homepage, https://will.astley.dev
Project-URL: Repository, https://github.com/pr1m8/pydevelop-docs
